vericode/__init__.py
vericode/vericode.py
vericode-1.0.2.dist-info/licenses/LICENSE
vericode-1.0.2.dist-info/METADATA
vericode-1.0.2.dist-info/WHEEL
vericode-1.0.2.dist-info/entry_points.txt
vericode-1.0.2.dist-info/top_level.txt
vericode-1.0.2.dist-info/RECORD
