Metadata-Version: 2.4
Name: vericode
Version: 1.0.2
Summary: Multi-language code verification tool
Author-email: Paul Nilsson <Paul.Nilsson@cern.ch>
License:                                  Apache License
License-File: LICENSE
Requires-Dist: pylint
Requires-Dist: flake8
Requires-Dist: pydocstyle
Dynamic: license-file
